{
    "userScenario": [
        {
            "number": 1,
            "users": [
                {
                    "userNumber": 1,
                    "registration": {
                        "fullName": "Tomás Acosta",
                        "email": "tomas.acosta@email.com",
                        "password": "H7k^Q9x@1Pw&R",
                        "repeatPassword": "H7k^Q9x@1Pw&R"
                    },
                    "login": {
                        "email": "tomas.acosta@email.com",
                        "password": "H7k^Q9x@1Pw&R"
                    }
                }
            ]
        }
    ]
}